tornado_debugger/__init__.py
tornado_debugger/debug.html
tornado_debugger/debug.py
tornado_debugger/mixins.py
tornado_debugger-0.9.2.dist-info/LICENSE.txt
tornado_debugger-0.9.2.dist-info/METADATA
tornado_debugger-0.9.2.dist-info/WHEEL
tornado_debugger-0.9.2.dist-info/top_level.txt
tornado_debugger-0.9.2.dist-info/RECORD
