Metadata-Version: 2.1
Name: tornado-debugger
Version: 0.9.2
Summary: A better exception printer for Tornado web server.
Home-page: https://www.github.com/bhch/tornado-debugger
Author: Bharat Chauhan
Author-email: tell.bhch@gmail.com
License: BSD-3-Clause
Classifier: Environment :: Web Environment
Classifier: Intended Audience :: Developers
Classifier: License :: OSI Approved :: BSD License
Classifier: Operating System :: OS Independent
Classifier: Programming Language :: Python
Classifier: Programming Language :: Python :: 3
Classifier: Programming Language :: Python :: 3 :: Only
Classifier: Programming Language :: Python :: 3.4
Classifier: Programming Language :: Python :: 3.5
Classifier: Programming Language :: Python :: 3.6
Classifier: Programming Language :: Python :: 3.7
Classifier: Programming Language :: Python :: 3.8
Classifier: Programming Language :: Python :: 3.9
Classifier: Programming Language :: Python :: 3.10
Classifier: Topic :: Internet :: WWW/HTTP
Classifier: Topic :: Internet :: WWW/HTTP :: Dynamic Content
Requires-Python: >=3.4
License-File: LICENSE.txt
Requires-Dist: tornado (>=5.1)
